CHANGELOG.md
LICENSE
README.md
application_settings/__init__.py
application_settings/_private/__init__.py
application_settings/_private/file_operations.py
application_settings/_private/file_operations_utils.py
application_settings/_private/json_file_operations.py
application_settings/_private/toml_file_operations.py
application_settings/configuring_base.py
application_settings/container_base.py
application_settings/container_section_base.py
application_settings/convenience.py
application_settings/parameter_kind.py
application_settings/py.typed
application_settings/settings_base.py
application_settings/type_notation_helper.py
application_settings-0.5.0.dist-info/LICENSE
application_settings-0.5.0.dist-info/METADATA
application_settings-0.5.0.dist-info/WHEEL
application_settings-0.5.0.dist-info/RECORD
