Metadata-Version: 2.1
Name: application_settings
Version: 0.5.0
Summary: For providing a python application with configuration and/or settings
Home-page: https://github.com/StockwatchDev/application_settings
License: MIT
Keywords: configuration,settings,dataclass,pydantic,toml
Author: Stockwatchdevs
Author-email: stockwatchdevs@gmail.com
Requires-Python: >=3.9
Classifier: Development Status :: 4 - Beta
Classifier: Intended Audience :: Developers
Classifier: License :: OSI Approved :: MIT License
Classifier: Natural Language :: English
Classifier: Operating System :: OS Independent
Classifier: Programming Language :: Python :: 3
Classifier: Programming Language :: Python :: 3.9
Classifier: Programming Language :: Python :: 3.10
Classifier: Programming Language :: Python :: 3.11
Classifier: Programming Language :: Python :: 3.12
Classifier: Topic :: Software Development :: Libraries :: Python Modules
Classifier: Typing :: Typed
Requires-Dist: attributes-doc (>=0.3.0)
Requires-Dist: loguru (>=0.7.0)
Requires-Dist: pathvalidate (>=2.5)
Requires-Dist: pydantic (>=2.0)
Requires-Dist: tomlkit (>=0.12)
Requires-Dist: typing-extensions (>=4.5.0) ; python_version < "3.12"
Project-URL: Changelog, https://stockwatchdev.github.io/application_settings/stable/CHANGELOG/
Project-URL: Documentation, https://stockwatchdev.github.io/application_settings/stable/
Project-URL: Repository, https://github.com/StockwatchDev/application_settings
